[
	{
		"name": "Club",
		"category": "Simple Melee Weapons",
		"cost": "1 sp",
		"damage_dice": "1d4",
		"damage_type": "bludgeoning",
		"weight": "2 lb.",
		"properties": [
			"light"
		]
	},
	{
		"name": "Dagger",
		"category": "Simple Melee Weapons",
		"cost": "2 gp",
		"damage_dice": "1d4",
		"damage_type": "piercing",
		"weight": "1 lb.",
		"properties": [
			"finesse",
			"light",
			"thrown (range 20/60)"
		]
	},
	{
		"name": "Greatclub",
		"category": "Simple Melee Weapons",
		"cost": "2 sp",
		"damage_dice": "1d8",
		"damage_type": "bludgeoning",
		"weight": "10 lb.",
		"properties": [
			"two-handed"
		]
	},
	{
		"name": "Handaxe",
		"category": "Simple Melee Weapons",
		"cost": "5 gp",
		"damage_dice": "1d6",
		"damage_type": "slashing",
		"weight": "2 lb.",
		"properties": [
			"light",
			"thrown (range 20/60)"
		]
	},
	{
		"name": "Javelin",
		"category": "Simple Melee Weapons",
		"cost": "5 sp",
		"damage_dice": "1d6",
		"damage_type": "piercing",
		"weight": "2 lb.",
		"properties": [
			"thrown (range 30/120)"
		]
	},
	{
		"name": "Light hammer",
		"category": "Simple Melee Weapons",
		"cost": "2 gp",
		"damage_dice": "1d4",
		"damage_type": "bludgeoning",
		"weight": "2 lb.",
		"properties": [
			"light",
			"thrown (range 20/60)"
		]
	},
	{
		"name": "Mace",
		"category": "Simple Melee Weapons",
		"cost": "5 gp",
		"damage_dice": "1d6",
		"damage_type": "bludgeoning",
		"weight": "4 lb.",
		"properties": []
	},
	{
		"name": "Quarterstaff",
		"category": "Simple Melee Weapons",
		"cost": "2 sp",
		"damage_dice": "1d6",
		"damage_type": "bludgeoning",
		"weight": "4 lb.",
		"properties": [
			"versatile (1d8)"
		]
	},
	{
		"name": "Sickle",
		"category": "Simple Melee Weapons",
		"cost": "1 gp",
		"damage_dice": "1d4",
		"damage_type": "slashing",
		"weight": "2 lb.",
		"properties": [
			"light"
		]
	},
	{
		"name": "Spear",
		"category": "Simple Melee Weapons",
		"cost": "1 gp",
		"damage_dice": "1d6",
		"damage_type": "piercing",
		"weight": "3 lb.",
		"properties": [
			"thrown (range 20/60)",
			"versatile (1d8)"
		]
	},
	{
		"name": "Crossbow, light",
		"category": "Simple Ranged Weapons",
		"cost": "25 gp",
		"damage_dice": "1d8",
		"damage_type": "piercing",
		"weight": "5 lb.",
		"properties": [
			"ammunition (range 80/320)",
			"loading",
			"two-handed"
		]
	},
	{
		"name": "Dart",
		"category": "Simple Ranged Weapons",
		"cost": "5 cp",
		"damage_dice": "1d4",
		"damage_type": "piercing",
		"weight": "1/4 lb.",
		"properties": [
			"finesse",
			"thrown (range 20/60)"
		]
	},
	{
		"name": "Shortbow",
		"category": "Simple Ranged Weapons",
		"cost": "25 gp",
		"damage_dice": "1d6",
		"damage_type": "piercing",
		"weight": "2 lb.",
		"properties": [
			"ammunition (range 80/320)",
			"two-handed"
		]
	},
	{
		"name": "Sling",
		"category": "Simple Ranged Weapons",
		"cost": "1 sp",
		"damage_dice": "1d4",
		"damage_type": "bludgeoning",
		"weight": "0 lb.",
		"properties": [
			"ammunition (range 30/120)"
		]
	},
	{
		"name": "Battleaxe",
		"category": "Martial Melee Weapons",
		"cost": "10 gp",
		"damage_dice": "1d8",
		"damage_type": "slashing",
		"weight": "4 lb.",
		"properties": [
			"versatile (1d10)"
		]
	},
	{
		"name": "Flail",
		"category": "Martial Melee Weapons",
		"cost": "10 gp",
		"damage_dice": "1d8",
		"damage_type": "bludgeoning",
		"weight": "2 lb.",
		"properties": []
	},
	{
		"name": "Glaive",
		"category": "Martial Melee Weapons",
		"cost": "20 gp",
		"damage_dice": "1d10",
		"damage_type": "slashing",
		"weight": "6 lb.",
		"properties": [
			"heavy",
			"reach",
			"two-handed"
		]
	},
	{
		"name": "Greataxe",
		"category": "Martial Melee Weapons",
		"cost": "30 gp",
		"damage_dice": "1d12",
		"damage_type": "slashing",
		"weight": "7 lb.",
		"properties": [
			"heavy",
			"two-handed"
		]
	},
	{
		"name": "Greatsword",
		"category": "Martial Melee Weapons",
		"cost": "50 gp",
		"damage_dice": "2d6",
		"damage_type": "slashing",
		"weight": "6 lb.",
		"properties": [
			"heavy",
			"two-handed"
		]
	},
	{
		"name": "Halberd",
		"category": "Martial Melee Weapons",
		"cost": "20 gp",
		"damage_dice": "1d10",
		"damage_type": "slashing",
		"weight": "6 lb.",
		"properties": [
			"heavy",
			"reach",
			"two-handed"
		]
	},
	{
		"name": "Lance",
		"category": "Martial Melee Weapons",
		"cost": "10 gp",
		"damage_dice": "1d12",
		"damage_type": "piercing",
		"weight": "6 lb.",
		"properties": [
			"reach",
			"special"
		]
	},
	{
		"name": "Longsword",
		"category": "Martial Melee Weapons",
		"cost": "15 gp",
		"damage_dice": "1d8",
		"damage_type": "slashing",
		"weight": "3 lb.",
		"properties": [
			"versatile (1d10)"
		]
	},
	{
		"name": "Maul",
		"category": "Martial Melee Weapons",
		"cost": "10 gp",
		"damage_dice": "2d6",
		"damage_type": "bludgeoning",
		"weight": "10 lb.",
		"properties": [
			"heavy",
			"two-handed"
		]
	},
	{
		"name": "Morningstar",
		"category": "Martial Melee Weapons",
		"cost": "15 gp",
		"damage_dice": "1d8",
		"damage_type": "piercing",
		"weight": "4 lb."
	},
	{
		"name": "Pike",
		"category": "Martial Melee Weapons",
		"cost": "5 gp",
		"damage_dice": "1d10",
		"damage_type": "piercing",
		"weight": "18 lb.",
		"properties": [
			"heavy",
			"reach",
			"two-handed"
		]
	},
	{
		"name": "Rapier",
		"category": "Martial Melee Weapons",
		"cost": "25 gp",
		"damage_dice": "1d8",
		"damage_type": "piercing",
		"weight": "2 lb.",
		"properties": [
			"finesse"
		]
	},
	{
		"name": "Scimitar",
		"category": "Martial Melee Weapons",
		"cost": "25 gp",
		"damage_dice": "1d6",
		"damage_type": "slashing",
		"weight": "3 lb.",
		"properties": [
			"finesse",
			"light"
		]
	},
	{
		"name": "Shortsword",
		"category": "Martial Melee Weapons",
		"cost": "10 gp",
		"damage_dice": "1d6",
		"damage_type": "piercing",
		"weight": "2 lb.",
		"properties": [
			"finesse",
			"light"
		]
	},
	{
		"name": "Trident",
		"category": "Martial Melee Weapons",
		"cost": "5 gp",
		"damage_dice": "1d6",
		"damage_type": "piercing",
		"weight": "4 lb.",
		"properties": [
			"thrown (range 20/60)",
			"versatile (1d8)"
		]
	},
	{
		"name": "War pick",
		"category": "Martial Melee Weapons",
		"cost": "5 gp",
		"damage_dice": "1d8",
		"damage_type": "piercing",
		"weight": "2 lb.",
		"properties": []
	},
	{
		"name": "Warhammer",
		"category": "Martial Melee Weapons",
		"cost": "15 gp",
		"damage_dice": "1d8",
		"damage_type": "bludgeoning",
		"weight": "2 lb.",
		"properties": [
			"versatile (1d10)"
		]
	},
	{
		"name": "Whip",
		"category": "Martial Melee Weapons",
		"cost": "2 gp",
		"damage_dice": "1d4",
		"damage_type": "slashing",
		"weight": "3 lb.",
		"properties": [
			"finesse",
			"reach"
		]
	},
	{
		"name": "Blowgun",
		"category": "Martial Ranged Weapons",
		"cost": "10 gp",
		"damage_dice": "1",
		"damage_type": "piercing",
		"weight": "1 lb.",
		"properties": [
			"ammunition (range 25/100)",
			"loading"
		]
	},
	{
		"name": "Crossbow, hand",
		"category": "Martial Ranged Weapons",
		"cost": "75 gp",
		"damage_dice": "1d6",
		"damage_type": "piercing",
		"weight": "3 lb.",
		"properties": [
			"ammunition (range 30/120)",
			"light",
			"loading"
		]
	},
	{
		"name": "Crossbow, heavy",
		"category": "Martial Ranged Weapons",
		"cost": "50 gp",
		"damage_dice": "1d10",
		"damage_type": "piercing",
		"weight": "18 lb.",
		"properties": [
			"ammunition (range 100/400)",
			"heavy",
			"loading",
			"two-handed"
		]
	},
	{
		"name": "Longbow",
		"category": "Martial Ranged Weapons",
		"cost": "50 gp",
		"damage_dice": "1d8",
		"damage_type": "piercing",
		"weight": "2 lb.",
		"properties": [
			"ammunition (range 150/600)",
			"heavy",
			"two-handed"
		]
	},
	{
		"name": "Net",
		"category": "Martial Ranged Weapons",
		"cost": "1 gp",
		"damage_dice": 0,
		"weight": "3 lb.",
		"properties": [
			"special",
			"thrown (range 5/15)"
		]
	}
]